async_dash/__init__.py
async_dash/monkey_patch_callback.py
async_dash/monkey_patch_callback_context.py
async_dash/monkey_patch_dash.py
async_dash-0.1.0a1.dist-info/WHEEL
async_dash-0.1.0a1.dist-info/METADATA
async_dash-0.1.0a1.dist-info/RECORD
