Metadata-Version: 2.1
Name: async-dash
Version: 0.1.0a1
Summary: Async port of the official Plotly Dash library
Home-page: https://github.com/snehilvj/async-dash
License: MIT
Keywords: dash,plotly,async,quart,flask
Author: Snehil Vijay
Author-email: snehilvj@outlook.com
Requires-Python: >=3.7
Classifier: Development Status :: 3 - Alpha
Classifier: Environment :: Web Environment
Classifier: Framework :: Dash
Classifier: Framework :: Flask
Classifier: Intended Audience :: Developers
Classifier: Intended Audience :: Education
Classifier: Intended Audience :: Financial and Insurance Industry
Classifier: Intended Audience :: Healthcare Industry
Classifier: Intended Audience :: Manufacturing
Classifier: Intended Audience :: Science/Research
Classifier: License :: OSI Approved :: MIT License
Classifier: Programming Language :: Python
Classifier: Programming Language :: Python :: 3
Classifier: Programming Language :: Python :: 3.10
Classifier: Programming Language :: Python :: 3.7
Classifier: Programming Language :: Python :: 3.8
Classifier: Programming Language :: Python :: 3.9
Classifier: Topic :: Database :: Front-Ends
Classifier: Topic :: Office/Business :: Financial :: Spreadsheet
Classifier: Topic :: Scientific/Engineering :: Visualization
Classifier: Topic :: Software Development :: Libraries :: Application Frameworks
Classifier: Topic :: Software Development :: Widget Sets
Requires-Dist: dash (>=2.2.0,<3.0.0)
Requires-Dist: quart (>=0.16.3,<0.17.0)
Project-URL: Documentation, https://github.com/snehilvj/async-dash
Project-URL: Repository, https://github.com/snehilvj/async-dash
